{
  "profile": {
    "account_id": 3547384,
    "personaname": "Topson",
    "name": "Topson",
    "plus": false,
    "cheese": 456,
    "steamid": "76561198830235426",
    "avatar": "https://steamcdn-a.akamaihd.net/steamcommunity/public/images/avatars/99/14.jpg",
    "avatarmedium": "https://steamcdn-a.akamaihd.net/steamcommunity/public/images/avatars/64/32_medium.jpg",
    "avatarfull": "https://steamcdn-a.akamaihd.net/steamcommunity/public/images/avatars/8/8_full.jpg",
    "profileurl": "https://steamcommunity.com/profiles/3547384",
    "last_login": "2025-07-05T16:16:41.259Z",
    "loccountrycode": "SEA",
    "status": "offline",
    "fh_unavailable": false,
    "is_contributor": false,
    "is_subscriber": false
  },
  "rank_tier": 77,
  "leaderboard_rank": 641,
  "total_matches": 2178,
  "win": 1231,
  "kda": 5.72,
  "gpm": 738,
  "xpm": 785,
  "avg_seconds_per_match": 2960
}