{
  "profile": {
    "account_id": 6866113,
    "personaname": "Bulba",
    "name": "Bulba",
    "plus": true,
    "cheese": 830,
    "steamid": "76561198428187102",
    "avatar": "https://steamcdn-a.akamaihd.net/steamcommunity/public/images/avatars/19/47.jpg",
    "avatarmedium": "https://steamcdn-a.akamaihd.net/steamcommunity/public/images/avatars/19/78_medium.jpg",
    "avatarfull": "https://steamcdn-a.akamaihd.net/steamcommunity/public/images/avatars/25/64_full.jpg",
    "profileurl": "https://steamcommunity.com/profiles/6866113",
    "last_login": "2025-07-01T18:59:53.717Z",
    "loccountrycode": "EU",
    "status": "offline",
    "fh_unavailable": false,
    "is_contributor": false,
    "is_subscriber": true
  },
  "rank_tier": 80,
  "leaderboard_rank": 294,
  "total_matches": 4357,
  "win": 1813,
  "kda": 7.5,
  "gpm": 392,
  "xpm": 525,
  "avg_seconds_per_match": 2086
}